bowler/__init__.py
bowler/helpers.py
bowler/imr.py
bowler/query.py
bowler/tool.py
bowler/type_inference.py
bowler/types.py
fissix/Grammar.txt
fissix/PatternGrammar.txt
fissix/__init__.py
fissix/btm_matcher.py
fissix/btm_utils.py
fissix/fixer_base.py
fissix/fixer_util.py
fissix/patcomp.py
fissix/pygram.py
fissix/pytree.py
fissix/refactor.py
fissix/pgen2/__init__.py
fissix/pgen2/conv.py
fissix/pgen2/driver.py
fissix/pgen2/grammar.py
fissix/pgen2/literals.py
fissix/pgen2/parse.py
fissix/pgen2/pgen.py
fissix/pgen2/token.py
fissix/pgen2/tokenize.py
paddle_upgrade_tool/__init__.py
paddle_upgrade_tool/__main__.py
paddle_upgrade_tool/common.py
paddle_upgrade_tool/filters.py
paddle_upgrade_tool/fixers.py
paddle_upgrade_tool/main.py
paddle_upgrade_tool/processors.py
paddle_upgrade_tool/refactor.py
paddle_upgrade_tool/spec.py
paddle_upgrade_tool/transformers.py
paddle_upgrade_tool/utils.py
paddle_upgrade_tool/tests/__init__.py
paddle_upgrade_tool/tests/test_refactor.py
tools/__init__.py
tools/click.py
tools/find_match_node.py
tools/find_pattern.py
paddle_upgrade_tool-0.0.27.dist-info/LICENSE
paddle_upgrade_tool-0.0.27.dist-info/METADATA
paddle_upgrade_tool-0.0.27.dist-info/WHEEL
paddle_upgrade_tool-0.0.27.dist-info/entry_points.txt
paddle_upgrade_tool-0.0.27.dist-info/top_level.txt
paddle_upgrade_tool-0.0.27.dist-info/RECORD
